flashbax/__init__.py
flashbax/conftest.py
flashbax/utils.py
flashbax/utils_test.py
flashbax/buffers/__init__.py
flashbax/buffers/conftest.py
flashbax/buffers/flat_buffer.py
flashbax/buffers/flat_buffer_test.py
flashbax/buffers/item_buffer.py
flashbax/buffers/item_buffer_test.py
flashbax/buffers/mixer.py
flashbax/buffers/mixer_test.py
flashbax/buffers/prioritised_flat_buffer.py
flashbax/buffers/prioritised_flat_buffer_test.py
flashbax/buffers/prioritised_item_buffer.py
flashbax/buffers/prioritised_item_buffer_test.py
flashbax/buffers/prioritised_trajectory_buffer.py
flashbax/buffers/prioritised_trajectory_buffer_test.py
flashbax/buffers/sum_tree.py
flashbax/buffers/sum_tree_test.py
flashbax/buffers/trajectory_buffer.py
flashbax/buffers/trajectory_buffer_test.py
flashbax/buffers/trajectory_queue.py
flashbax/buffers/trajectory_queue_test.py
flashbax/vault/__init__.py
flashbax/vault/vault.py
flashbax/vault/vault_test.py
flashbax-0.1.3.dist-info/METADATA
flashbax-0.1.3.dist-info/WHEEL
flashbax-0.1.3.dist-info/licenses/LICENSE
flashbax-0.1.3.dist-info/RECORD
