Metadata-Version: 2.4
Name: flashbax
Version: 0.1.3
Summary: Flashbax is an experience replay library oriented around JAX. Tailored to integrate seamlessly with JAX's Just-In-Time (JIT) compilation.
Project-URL: Homepage, https://github.com/instadeepai/flashbax
Project-URL: Bug Tracker, https://github.com/instadeepai/flashbax/issues
Project-URL: Repository, https://github.com/instadeepai/flashbax.git
Author-email: InstaDeep <hello@instadeep.com>
License-File: LICENSE
Keywords: jax,memory,python,reinforcement-learning
Classifier: Development Status :: 2 - Pre-Alpha
Classifier: Environment :: Console
Classifier: Intended Audience :: Developers
Classifier: Intended Audience :: Science/Research
Classifier: License :: OSI Approved :: Apache Software License
Classifier: Operating System :: OS Independent
Classifier: Programming Language :: Python :: 3.9
Classifier: Topic :: Scientific/Engineering :: Artificial Intelligence
Classifier: Topic :: Software Development :: Libraries :: Python Modules
Requires-Python: >=3.9
Requires-Dist: chex>=0.1.8
Requires-Dist: flax>=0.6.11
Requires-Dist: jax>=0.4.25
Requires-Dist: jaxlib>=0.4.20
Requires-Dist: numpy>=1.19.5
Requires-Dist: tensorstore>=0.1.51
Requires-Dist: typing-extensions>=4.6.0
Provides-Extra: dev
Requires-Dist: black>=23.7.0; extra == 'dev'
Requires-Dist: coverage>=6.5.0; extra == 'dev'
Requires-Dist: flake8>=6.0.0; extra == 'dev'
Requires-Dist: isort>=5.12.0; extra == 'dev'
Requires-Dist: mkdocs-git-revision-date-plugin==0.3.2; extra == 'dev'
Requires-Dist: mkdocs-include-markdown-plugin==6.0.1; extra == 'dev'
Requires-Dist: mkdocs-material==9.4.2; extra == 'dev'
Requires-Dist: mkdocs-mermaid2-plugin==1.1.1; extra == 'dev'
Requires-Dist: mkdocs==1.5.3; extra == 'dev'
Requires-Dist: mkdocstrings[python]==0.23.0; extra == 'dev'
Requires-Dist: mknotebooks==0.8.0; extra == 'dev'
Requires-Dist: mypy>=1.8.0; extra == 'dev'
Requires-Dist: pre-commit>=2.20.0; extra == 'dev'
Requires-Dist: pytest-cov>=4.00; extra == 'dev'
Requires-Dist: pytest-xdist>=3.0.2; extra == 'dev'
Requires-Dist: pytest>=7.4.2; extra == 'dev'
Provides-Extra: examples
Requires-Dist: distrax; extra == 'examples'
Requires-Dist: dm-haiku; extra == 'examples'
Requires-Dist: gymnasium; extra == 'examples'
Requires-Dist: jumanji; extra == 'examples'
Requires-Dist: jupyterlab; extra == 'examples'
Requires-Dist: matplotlib; extra == 'examples'
Requires-Dist: optax; extra == 'examples'
Requires-Dist: rlax; extra == 'examples'
Requires-Dist: seaborn; extra == 'examples'
